{
  "id": "1738",
  "name": "Matt Moorhouse",
  "sex": "Male",
  "category": "Vet",
  "club": "Preston CC",
  "bar": {
    "short": [],
    "medium": [],
    "long": [
      {
        "eventId": "14959",
        "raceCategory": "long",
        "name": "Derwentside Cc (Lakes & Lancs Spoco)",
        "course": "M40",
        "distance": 40,
        "fee": 9.5,
        "date": "07 May 2017",
        "club": "Preston CC",
        "position": "3",
        "time": "1:46:29",
        "speed": "22.54 Mph",
        "bar": 0,
        "barPosition": 121,
        "vbar": 0,
        "lbar": 0,
        "jbar": 0
      }
    ],
    "shortCount": 0,
    "mediumCount": 0,
    "longCount": 1,
    "allCount": 1,
    "complete": false,
    "canComplete": true,
    "averagePointsPerShortRace": 0,
    "averagePointsPerMediumRace": 0,
    "averagePointsPerLongRace": 0,
    "averagePointsPerRace": 0,
    "remainingShortPoints": 240,
    "remainingMediumPoints": 360,
    "remainingLongPoints": 120,
    "remainingPoints": 720,
    "predictedFinalPoints": 0,
    "pointsDirection": 2,
    "regionalChampionship": {
      "raced": 0,
      "totalPoints": 0
    },
    "totals": {
      "short": 0,
      "medium": 0,
      "long": 0,
      "grand": 0
    },
    "predictedFinalPosition": 315
  },
  "vbar": {
    "short": [],
    "medium": [],
    "long": [],
    "shortCount": 0,
    "mediumCount": 0,
    "longCount": 0,
    "allCount": 0,
    "complete": false,
    "averagePointsPerShortRace": 0,
    "averagePointsPerMediumRace": 0,
    "averagePointsPerLongRace": 0,
    "averagePointsPerRace": 0,
    "remainingShortPoints": 240,
    "remainingMediumPoints": 360,
    "remainingLongPoints": 120,
    "remainingPoints": 720,
    "predictedFinalPoints": 0,
    "pointsDirection": 0,
    "regionalChampionship": {
      "raced": 0,
      "totalPoints": 0
    },
    "totals": {
      "short": 0,
      "medium": 0,
      "long": 0,
      "grand": 0
    }
  },
  "lbar": {
    "short": [],
    "medium": [],
    "long": [],
    "shortCount": 0,
    "mediumCount": 0,
    "longCount": 0,
    "allCount": 0,
    "complete": false,
    "averagePointsPerShortRace": 0,
    "averagePointsPerMediumRace": 0,
    "averagePointsPerLongRace": 0,
    "averagePointsPerRace": 0,
    "remainingShortPoints": 240,
    "remainingMediumPoints": 360,
    "remainingLongPoints": 120,
    "remainingPoints": 720,
    "predictedFinalPoints": 0,
    "pointsDirection": 0,
    "regionalChampionship": {
      "raced": 0,
      "totalPoints": 0
    },
    "totals": {
      "short": 0,
      "medium": 0,
      "long": 0,
      "grand": 0
    }
  },
  "jbar": {
    "short": [],
    "medium": [],
    "long": [],
    "shortCount": 0,
    "mediumCount": 0,
    "longCount": 0,
    "allCount": 0,
    "complete": false,
    "canComplete": true,
    "averagePointsPerShortRace": 0,
    "averagePointsPerMediumRace": 0,
    "averagePointsPerLongRace": 0,
    "averagePointsPerRace": 0,
    "remainingShortPoints": 240,
    "remainingMediumPoints": 240,
    "remainingLongPoints": 0,
    "remainingPoints": 480,
    "predictedFinalPoints": 0,
    "pointsDirection": 0,
    "regionalChampionship": {
      "raced": 0,
      "totalPoints": 0
    },
    "totals": {
      "short": 0,
      "medium": 0,
      "long": 0,
      "grand": 0
    }
  },
  "races": [
    {
      "eventId": "14959",
      "raceCategory": "long",
      "name": "Derwentside Cc (Lakes & Lancs Spoco)",
      "course": "M40",
      "distance": 40,
      "fee": 9.5,
      "date": "07 May 2017",
      "club": "Preston CC",
      "position": "3",
      "time": "1:46:29",
      "speed": "22.54 Mph",
      "bar": 0,
      "barPosition": 121,
      "vbar": 0,
      "lbar": 0,
      "jbar": 0
    },
    {
      "eventId": "15017",
      "raceCategory": "long",
      "name": "Tyneside Vagabonds Cc (Lakes & Lancs Spoco)",
      "course": "M47",
      "distance": 47,
      "fee": 11,
      "date": "14 May 2017",
      "club": "Preston CC",
      "position": "DNS",
      "time": "",
      "speed": "NaN Mph",
      "bar": 0,
      "barPosition": 121,
      "vbar": 0,
      "lbar": 0,
      "jbar": 0
    }
  ],
  "position": 365,
  "barHistory": [
    {
      "eventId": "14959",
      "date": "07 May 2017",
      "name": "M40",
      "points": {
        "short": 0,
        "medium": 0,
        "long": 0,
        "grand": 0
      },
      "position": 264
    },
    {
      "eventId": "15017",
      "date": "14 May 2017",
      "name": "M47",
      "points": {
        "short": 0,
        "medium": 0,
        "long": 0,
        "grand": 0
      },
      "position": 277
    },
    {
      "eventId": "15075",
      "date": "20 May 2017",
      "name": "M102B",
      "points": {
        "short": 0,
        "medium": 0,
        "long": 0,
        "grand": 0
      },
      "position": 283
    },
    {
      "eventId": "15161",
      "date": "28 May 2017",
      "name": "M107",
      "points": {
        "short": 0,
        "medium": 0,
        "long": 0,
        "grand": 0
      },
      "position": 295
    },
    {
      "eventId": "15202",
      "date": "04 June 2017",
      "name": "M24.8",
      "points": {
        "short": 0,
        "medium": 0,
        "long": 0,
        "grand": 0
      },
      "position": 310
    },
    {
      "eventId": "15232",
      "date": "10 June 2017",
      "name": "M13",
      "points": {
        "short": 0,
        "medium": 0,
        "long": 0,
        "grand": 0
      },
      "position": 319
    },
    {
      "eventId": "15260",
      "date": "11 June 2017",
      "name": "M2511",
      "points": {
        "short": 0,
        "medium": 0,
        "long": 0,
        "grand": 0
      },
      "position": 324
    },
    {
      "eventId": "15334",
      "date": "18 June 2017",
      "name": "M2510",
      "points": {
        "short": 0,
        "medium": 0,
        "long": 0,
        "grand": 0
      },
      "position": 332
    },
    {
      "eventId": "15378",
      "date": "24 June 2017",
      "name": "M9",
      "points": {
        "short": 0,
        "medium": 0,
        "long": 0,
        "grand": 0
      },
      "position": 339
    },
    {
      "eventId": "15392",
      "date": "25 June 2017",
      "name": "M254",
      "points": {
        "short": 0,
        "medium": 0,
        "long": 0,
        "grand": 0
      },
      "position": 342
    },
    {
      "eventId": "15524",
      "date": "09 July 2017",
      "name": "M2511",
      "points": {
        "short": 0,
        "medium": 0,
        "long": 0,
        "grand": 0
      },
      "position": 348
    },
    {
      "eventId": "15534",
      "date": "12 July 2017",
      "name": "M102B",
      "points": {
        "short": 0,
        "medium": 0,
        "long": 0,
        "grand": 0
      },
      "position": 350
    },
    {
      "eventId": "15587",
      "date": "15 July 2017",
      "name": "M14",
      "points": {
        "short": 0,
        "medium": 0,
        "long": 0,
        "grand": 0
      },
      "position": 357
    },
    {
      "eventId": "15601",
      "date": "22 July 2017",
      "name": "M26",
      "points": {
        "short": 0,
        "medium": 0,
        "long": 0,
        "grand": 0
      },
      "position": 358
    },
    {
      "eventId": "15675",
      "date": "30 July 2017",
      "name": "M254",
      "points": {
        "short": 0,
        "medium": 0,
        "long": 0,
        "grand": 0
      },
      "position": 360
    },
    {
      "eventId": "15710",
      "date": "06 August 2017",
      "name": "M509",
      "points": {
        "short": 0,
        "medium": 0,
        "long": 0,
        "grand": 0
      },
      "position": 363
    },
    {
      "eventId": "15741",
      "date": "13 August 2017",
      "name": "M100/20",
      "points": {
        "short": 0,
        "medium": 0,
        "long": 0,
        "grand": 0
      },
      "position": 363
    },
    {
      "eventId": "15766",
      "date": "19 August 2017",
      "name": "M21",
      "points": {
        "short": 0,
        "medium": 0,
        "long": 0,
        "grand": 0
      },
      "position": 365
    }
  ],
  "tags": [
    {
      "cssclass": "tag is-black",
      "text": "1 x DNS"
    }
  ],
  "rivals": [
    {
      "position": 1,
      "id": "3625",
      "pointsDirection": 0,
      "barPredictedFinalPosition": 1,
      "name": "Adam Wild",
      "club": "Tyneside Vagabonds CC",
      "averagePointsPerRace": 119.83333333333333,
      "predictedFinalPoints": 719,
      "grandTotal": 719,
      "complete": true,
      "canComplete": true,
      "regionalChampionshipPoints": 239
    },
    {
      "position": 362,
      "id": "16523",
      "pointsDirection": 2,
      "barPredictedFinalPosition": 362,
      "name": "Marcus Cram",
      "club": "Castle Tri",
      "averagePointsPerRace": 0,
      "predictedFinalPoints": 0,
      "grandTotal": 0,
      "complete": false,
      "canComplete": true,
      "regionalChampionshipPoints": 0
    },
    {
      "position": 363,
      "id": "13879",
      "pointsDirection": 2,
      "barPredictedFinalPosition": 363,
      "name": "Callam Stewart",
      "club": "Army Cycling Union",
      "averagePointsPerRace": 0,
      "predictedFinalPoints": 0,
      "grandTotal": 0,
      "complete": false,
      "canComplete": true,
      "regionalChampionshipPoints": 0
    },
    {
      "position": 364,
      "id": "16038",
      "pointsDirection": 2,
      "barPredictedFinalPosition": 364,
      "name": "Ian Staines",
      "club": "NE31",
      "averagePointsPerRace": 0,
      "predictedFinalPoints": 0,
      "grandTotal": 0,
      "complete": false,
      "canComplete": true,
      "regionalChampionshipPoints": 0
    },
    {
      "position": 365,
      "id": "409",
      "pointsDirection": 2,
      "barPredictedFinalPosition": 365,
      "name": "Neil Withington",
      "club": "Beacon Wheelers",
      "averagePointsPerRace": 0,
      "predictedFinalPoints": 0,
      "grandTotal": 0,
      "complete": false,
      "canComplete": true,
      "regionalChampionshipPoints": 0
    },
    {
      "position": 366,
      "id": "849",
      "pointsDirection": 2,
      "barPredictedFinalPosition": 366,
      "name": "Dan Evans",
      "club": "Adept Precision RT",
      "averagePointsPerRace": 0,
      "predictedFinalPoints": 0,
      "grandTotal": 0,
      "complete": false,
      "canComplete": true,
      "regionalChampionshipPoints": 0
    },
    {
      "position": 367,
      "id": "1109",
      "pointsDirection": 2,
      "barPredictedFinalPosition": 367,
      "name": "Tim Humphries",
      "club": "Team Swift",
      "averagePointsPerRace": 0,
      "predictedFinalPoints": 0,
      "grandTotal": 0,
      "complete": false,
      "canComplete": true,
      "regionalChampionshipPoints": 0
    },
    {
      "position": 368,
      "id": "7366",
      "pointsDirection": 2,
      "barPredictedFinalPosition": 368,
      "name": "Jeremy Prodger",
      "club": "Beacon Wheelers",
      "averagePointsPerRace": 0,
      "predictedFinalPoints": 0,
      "grandTotal": 0,
      "complete": false,
      "canComplete": true,
      "regionalChampionshipPoints": 0
    }
  ]
}